odoo/addons/mass_mailing_custom_unsubscribe_event/README.rst
odoo/addons/mass_mailing_custom_unsubscribe_event/__init__.py
odoo/addons/mass_mailing_custom_unsubscribe_event/__manifest__.py
odoo/addons/mass_mailing_custom_unsubscribe_event/i18n/mass_mailing_custom_unsubscribe_event.pot
odoo/addons/mass_mailing_custom_unsubscribe_event/models/__init__.py
odoo/addons/mass_mailing_custom_unsubscribe_event/models/event_registration.py
odoo/addons/mass_mailing_custom_unsubscribe_event/readme/CONTRIBUTORS.rst
odoo/addons/mass_mailing_custom_unsubscribe_event/readme/DESCRIPTION.rst
odoo/addons/mass_mailing_custom_unsubscribe_event/readme/USAGE.rst
odoo/addons/mass_mailing_custom_unsubscribe_event/static/description/icon.png
odoo/addons/mass_mailing_custom_unsubscribe_event/static/description/index.html
odoo/addons/mass_mailing_custom_unsubscribe_event/views/event_registration_views.xml
odoo12_addon_mass_mailing_custom_unsubscribe_event-12.0.1.0.1.dist-info/METADATA
odoo12_addon_mass_mailing_custom_unsubscribe_event-12.0.1.0.1.dist-info/WHEEL
odoo12_addon_mass_mailing_custom_unsubscribe_event-12.0.1.0.1.dist-info/top_level.txt
odoo12_addon_mass_mailing_custom_unsubscribe_event-12.0.1.0.1.dist-info/RECORD
