Metadata-Version: 2.1
Name: odoo12-addon-mass-mailing-custom-unsubscribe-event
Version: 12.0.1.0.1
Summary: Allow to unsubscribe discretely from an event
Home-page: https://github.com/OCA/social
Author: Tecnativa, Odoo Community Association (OCA)
Author-email: support@odoo-community.org
License: AGPL-3
Platform: UNKNOWN
Classifier: Programming Language :: Python
Classifier: Framework :: Odoo
Classifier: License :: OSI Approved :: GNU Affero General Public License v3
Requires-Python: >=3.5
Requires-Dist: odoo12-addon-mass-mailing-custom-unsubscribe
Requires-Dist: odoo (<12.1dev,>=12.0a)
